termux/__init__.py
termux/common/__init__.py
termux/common/utils.py
termux/termux.py
termux_python-0.1.0.dist-info/WHEEL
termux_python-0.1.0.dist-info/METADATA
termux_python-0.1.0.dist-info/RECORD
