Metadata-Version: 2.1
Name: termux-python
Version: 0.1.0
Summary: termux python bindings
Home-page: https://github.com/mlvl42/termux_python
License: MIT
Author: mlvl42
Author-email: melvil.guillaume@gmail.com
Requires-Python: >=3.10,<4.0
Classifier: License :: OSI Approved :: MIT License
Classifier: Programming Language :: Python :: 3
Classifier: Programming Language :: Python :: 3.10
Project-URL: Repository, https://github.com/mlvl42/termux_python
